lazydocs/__init__.py
lazydocs/_about.py
lazydocs/_cli.py
lazydocs/generation.py
lazydocs-0.4.8.dist-info/LICENSE
lazydocs-0.4.8.dist-info/METADATA
lazydocs-0.4.8.dist-info/WHEEL
lazydocs-0.4.8.dist-info/entry_points.txt
lazydocs-0.4.8.dist-info/top_level.txt
lazydocs-0.4.8.dist-info/RECORD
