Metadata-Version: 2.1
Name: lazydocs
Version: 0.4.8
Summary: Generate markdown API documentation for Google-style Python docstring.
Home-page: https://github.com/ml-tooling/lazydocs
Author: ML Tooling Team
Author-email: team@mltooling.org
License: MIT
Project-URL: Changelog, https://github.com/ml-tooling/lazydocs/releases
Project-URL: Issue Tracker, https://github.com/ml-tooling/lazydocs/issues
Project-URL: Documentation, https://github.com/ml-tooling/lazydocs#documentation
Project-URL: Source, https://github.com/ml-tooling/lazydocs
Platform: UNKNOWN
Classifier: Development Status :: 4 - Beta
Classifier: Intended Audience :: Developers
Classifier: Intended Audience :: Science/Research
Classifier: License :: OSI Approved :: MIT License
Classifier: Natural Language :: English
Classifier: Operating System :: OS Independent
Classifier: Programming Language :: Python :: 3 :: Only
Classifier: Programming Language :: Python :: 3
Classifier: Programming Language :: Python :: 3.6
Classifier: Programming Language :: Python :: 3.7
Classifier: Programming Language :: Python :: 3.8
Classifier: Programming Language :: Python :: 3.9
Classifier: Programming Language :: Python :: Implementation :: PyPy
Classifier: Programming Language :: Python :: Implementation :: CPython
Classifier: Topic :: Software Development :: Libraries
Classifier: Topic :: Software Development :: Libraries :: Python Modules
Classifier: Topic :: Documentation
Classifier: Topic :: Documentation :: Sphinx
Classifier: Topic :: Text Processing :: Markup :: Markdown
Classifier: Topic :: Utilities
Requires-Python: >=3.6
Provides-Extra: dev
